{
  "products": [
    {
      "id": 1,
      "category": "mujer",
      "name": "Zapato de Tacón Rojo",
      "description": "Elegante y cómodo",
      "price": 1200,
      "size": [35, 36, 37, 38],
      "image": "red-heels.jpeg"
    },
    {
      "id": 2,
      "category": "mujer",
      "name": "Zapato de Tacón Rojo Oscuro",
      "description": "Elegante y perrísimo",
      "price": 2200,
      "size": [36, 37, 38, 39],
      "image": "cherry-heels.jpeg"
    },
    {
      "id": 3,
      "category": "mujer",
      "name": "Plataforma tipo Sandalias",
      "description": "Look muy del 2000's",
      "price": 700,
      "size": [35, 36, 37, 38],
      "image": "heart-heleed.jpeg"
    },
    {
      "id": 5,
      "category": "hombre",
      "name": "Zapato Casual Negro",
      "description": "Perfecto para eventos formales",
      "price": 1500,
      "size": [40, 41, 42, 43],
      "image": "black-shoes.jpeg"
    },
    {
      "id": 6,
      "category": "hombre",
      "name": "Zapato Vans",
      "description": "Perfecto para eventos casuales",
      "price": 500,
      "size": [40, 41, 42, 43],
      "image": "vans-shoes.jpeg"
    },
    {
      "id": 7,
      "category": "hombre",
      "name": "Zapato Air Force One",
      "description": "Perfecto para eventos casuales",
      "price": 850,
      "size": [40, 41, 42, 43],
      "image": "af1-force.jpeg"
    }
  ]
}
